MANIFEST.in
README.md
setup.cfg
setup.py
pispec/__init__.py
pispec/interpolate_ct_spectra.py
pispec/utils.py
pispec.egg-info/PKG-INFO
pispec.egg-info/SOURCES.txt
pispec.egg-info/dependency_links.txt
pispec.egg-info/not-zip-safe
pispec.egg-info/top_level.txt