Metadata-Version: 1.1
Name: pispec
Version: 0.1
Summary: Prototype package for computing photon injection spectra
Home-page: https://github.com/borisbolliet/pi_spec
Author: Boris Bolliet
Author-email: boris.bolliet@gmail.com
License: UNKNOWN
Download-URL: https://github.com/borisbolliet/pi_spec/archive/master.zip
Platform: UNKNOWN
